joshbasiccalculator/__init__.py
joshbasiccalculator/main.py
jaibasiccalculator-0.0.2.dist-info/LICENCE.txt
jaibasiccalculator-0.0.2.dist-info/METADATA
jaibasiccalculator-0.0.2.dist-info/WHEEL
jaibasiccalculator-0.0.2.dist-info/top_level.txt
jaibasiccalculator-0.0.2.dist-info/RECORD
